Klaksik1.py
klaksik1-1.0.1.dist-info/WHEEL
klaksik1-1.0.1.dist-info/METADATA
klaksik1-1.0.1.dist-info/RECORD
