Metadata-Version: 2.1
Name: klaksik1
Version: 1.0.1
Summary: i`m love minecraft
Author: Klaksik
Author-email: vsevolod2008cash@gmail.com
Requires-Python: >=3.9,<4.0
Classifier: Programming Language :: Python :: 3
Classifier: Programming Language :: Python :: 3.10
Classifier: Programming Language :: Python :: 3.9
